scanpy_scripts/__init__.py
scanpy_scripts/cli.py
scanpy_scripts/click_utils.py
scanpy_scripts/cmd_options.py
scanpy_scripts/cmd_utils.py
scanpy_scripts/cmds.py
scanpy_scripts/obj_utils.py
scanpy_scripts/lib/__init__.py
scanpy_scripts/lib/_bbknn.py
scanpy_scripts/lib/_combat.py
scanpy_scripts/lib/_diffexp.py
scanpy_scripts/lib/_diffmap.py
scanpy_scripts/lib/_dpt.py
scanpy_scripts/lib/_fdg.py
scanpy_scripts/lib/_filter.py
scanpy_scripts/lib/_hvg.py
scanpy_scripts/lib/_leiden.py
scanpy_scripts/lib/_louvain.py
scanpy_scripts/lib/_mnn.py
scanpy_scripts/lib/_neighbors.py
scanpy_scripts/lib/_norm.py
scanpy_scripts/lib/_paga.py
scanpy_scripts/lib/_pca.py
scanpy_scripts/lib/_read.py
scanpy_scripts/lib/_scrublet.py
scanpy_scripts/lib/_tsne.py
scanpy_scripts/lib/_umap.py
scanpy_scripts-1.9.301.data/scripts/scanpy-scripts-tests.bats
scanpy_scripts-1.9.301.dist-info/LICENSE
scanpy_scripts-1.9.301.dist-info/METADATA
scanpy_scripts-1.9.301.dist-info/WHEEL
scanpy_scripts-1.9.301.dist-info/entry_points.txt
scanpy_scripts-1.9.301.dist-info/top_level.txt
scanpy_scripts-1.9.301.dist-info/RECORD
