Metadata-Version: 2.1
Name: scanpy-scripts
Version: 1.9.301
Summary: Scripts for using scanpy from the command line
Home-page: https://github.com/ebi-gene-expression-group/scanpy-scripts
Author: nh3
Author-email: nh3@users.noreply.github.com
License-File: LICENSE
Requires-Dist: scanpy ==1.9.3
Requires-Dist: louvain
Requires-Dist: igraph
Requires-Dist: leidenalg
Requires-Dist: loompy
Requires-Dist: Click <8
Requires-Dist: harmonypy >=0.0.5
Requires-Dist: bbknn <1.6.0,>=1.5.0
Requires-Dist: mnnpy >=0.1.9.5
Requires-Dist: scipy <1.9.0
Requires-Dist: scikit-learn <1.3.0
Requires-Dist: scrublet
Requires-Dist: fa2
